{
    "statusCode": 200,
    "timeStamp": 1421888480,
    "message": "Ok",
    "debugInfo": "duplicateTeachersFilter is enable",
    "meta": null,
    "data": [
        {
            "lesson_id": "6961",
            "group_id": "461",
            "day_number": "1",
            "day_name": "Понеділок",
            "lesson_name": "Ін. мова проф-1. Проф",
            "lesson_full_name": "Іноземна мова професійного спрямування -1. Іноземна мова професійного спрямування",
            "lesson_number": "2",
            "lesson_room": "531-18",
            "lesson_type": "Прак",
            "teacher_name": "",
            "lesson_week": "1",
            "time_start": "10:25:00",
            "time_end": "12:00:00",
            "rate": "1",
            "teachers": [],
            "rooms": [
                {
                    "room_id": "21",
                    "room_name": "531-18 Прак",
                    "room_latitude": "50.447021",
                    "room_longitude": "30.456021"
                }
            ]
        },
        {
            "lesson_id": "6966",
            "group_id": "461",
            "day_number": "1",
            "day_name": "Понеділок",
            "lesson_name": "ОПСПІ",
            "lesson_full_name": "Основи теорії інформаційних процесів-2.Основи побудови систем передачі інформації",
            "lesson_number": "3",
            "lesson_room": "307-18",
            "lesson_type": "Лек",
            "teacher_name": "ст.вик. Моргаль О. М.",
            "lesson_week": "1",
            "time_start": "12:20:00",
            "time_end": "13:55:00",
            "rate": "1",
            "teachers": [
                {
                    "teacher_id": "2185",
                    "teacher_name": "Моргаль Олег Михайлович",
                    "teacher_full_name": "старший викладач Моргаль Олег Михайлович",
                    "teacher_short_name": "ст.вик. Моргаль О. М.",
                    "teacher_url": "http://rozklad.kpi.ua/Schedules/ViewSchedule.aspx?v=48c84c9c-7af8-4c08-9c5a-4045aace8756"
                }
            ],
            "rooms": [
                {
                    "room_id": "23",
                    "room_name": "307-18 Лек",
                    "room_latitude": "50.447021",
                    "room_longitude": "30.456021"
                }
            ]
        },
        {
            "lesson_id": "6971",
            "group_id": "461",
            "day_number": "1",
            "day_name": "Понеділок",
            "lesson_name": "Правознавство",
            "lesson_full_name": "Правознавство",
            "lesson_number": "4",
            "lesson_room": "231-18",
            "lesson_type": "Прак",
            "teacher_name": "",
            "lesson_week": "1",
            "time_start": "14:15:00",
            "time_end": "15:50:00",
            "rate": "0.5",
            "teachers": [],
            "rooms": [
                {
                    "room_id": "581",
                    "room_name": "231-18 0,5 Прак",
                    "room_latitude": "50.447021",
                    "room_longitude": "30.456021"
                }
            ]
        },
        {
            "lesson_id": "6962",
            "group_id": "461",
            "day_number": "2",
            "day_name": "Вівторок",
            "lesson_name": "Терія С та СА",
            "lesson_full_name": "Теорія систем та системний аналіз",
            "lesson_number": "2",
            "lesson_room": "304-18",
            "lesson_type": "Лек",
            "teacher_name": "доц. Кравець П. І.",
            "lesson_week": "1",
            "time_start": "10:25:00",
            "time_end": "12:00:00",
            "rate": "1",
            "teachers": [
                {
                    "teacher_id": "1629",
                    "teacher_name": "Кравець Петро Іванович",
                    "teacher_full_name": "доцент Кравець Петро Іванович",
                    "teacher_short_name": "доц. Кравець П. І.",
                    "teacher_url": "http://rozklad.kpi.ua/Schedules/ViewSchedule.aspx?v=2e64a2a9-39d1-4074-9af3-e9f09094fc3e"
                }
            ],
            "rooms": [
                {
                    "room_id": "20",
                    "room_name": "304-18 Лек",
                    "room_latitude": "50.447021",
                    "room_longitude": "30.456021"
                }
            ]
        },
        {
            "lesson_id": "6967",
            "group_id": "461",
            "day_number": "2",
            "day_name": "Вівторок",
            "lesson_name": "ППСАУ1",
            "lesson_full_name": "Проектування пристроїв та систем автоматики і управління -1. Проектування пристроїв АУ",
            "lesson_number": "3",
            "lesson_room": "304-18",
            "lesson_type": "Лек",
            "teacher_name": "доц. Юрчук Л. Ю.",
            "lesson_week": "1",
            "time_start": "12:20:00",
            "time_end": "13:55:00",
            "rate": "1",
            "teachers": [
                {
                    "teacher_id": "3848",
                    "teacher_name": "Юрчук Леонід Юрійович",
                    "teacher_full_name": "доцент Юрчук Леонід Юрійович",
                    "teacher_short_name": "доц. Юрчук Л. Ю.",
                    "teacher_url": "http://rozklad.kpi.ua/Schedules/ViewSchedule.aspx?v=a4fcf5d2-4937-4524-9157-86cbde69a498"
                }
            ],
            "rooms": [
                {
                    "room_id": "20",
                    "room_name": "304-18 Лек",
                    "room_latitude": "50.447021",
                    "room_longitude": "30.456021"
                }
            ]
        },
        {
            "lesson_id": "6972",
            "group_id": "461",
            "day_number": "2",
            "day_name": "Вівторок",
            "lesson_name": "ППСАУ1",
            "lesson_full_name": "Проектування пристроїв та систем автоматики і управління -1. Проектування пристроїв АУ",
            "lesson_number": "4",
            "lesson_room": "309-18",
            "lesson_type": "Лаб",
            "teacher_name": "доц. Юрчук Л. Ю., ст.вик. Долина В. Г.",
            "lesson_week": "1",
            "time_start": "14:15:00",
            "time_end": "15:50:00",
            "rate": "1",
            "teachers": [
                {
                    "teacher_id": "3848",
                    "teacher_name": "Юрчук Леонід Юрійович",
                    "teacher_full_name": "доцент Юрчук Леонід Юрійович",
                    "teacher_short_name": "доц. Юрчук Л. Ю.",
                    "teacher_url": "http://rozklad.kpi.ua/Schedules/ViewSchedule.aspx?v=a4fcf5d2-4937-4524-9157-86cbde69a498"
                },
                {
                    "teacher_id": "957",
                    "teacher_name": "Долина Віктор Георгійович",
                    "teacher_full_name": "старший викладач Долина Віктор Георгійович",
                    "teacher_short_name": "ст.вик. Долина В. Г.",
                    "teacher_url": "http://rozklad.kpi.ua/Schedules/ViewSchedule.aspx?v=78a5b574-b05e-432b-919d-95f2f165ef36"
                }
            ],
            "rooms": [
                {
                    "room_id": "28",
                    "room_name": "309-18 Лаб",
                    "room_latitude": "50.447021",
                    "room_longitude": "30.456021"
                }
            ]
        },
        {
            "lesson_id": "6963",
            "group_id": "461",
            "day_number": "3",
            "day_name": "Середа",
            "lesson_name": "Цифр. СУ",
            "lesson_full_name": "Теорія автоматичного управління -2. Теорія цифрових систем управління",
            "lesson_number": "2",
            "lesson_room": "534-18",
            "lesson_type": "Лаб",
            "teacher_name": "доц. Репнікова Н. Б., ст.вик. Писаренко А. В.",
            "lesson_week": "1",
            "time_start": "10:25:00",
            "time_end": "12:00:00",
            "rate": "1",
            "teachers": [
                {
                    "teacher_id": "2768",
                    "teacher_name": "Репнікова Наталія Борисівна",
                    "teacher_full_name": "доцент Репнікова Наталія Борисівна",
                    "teacher_short_name": "доц. Репнікова Н. Б.",
                    "teacher_url": "http://rozklad.kpi.ua/Schedules/ViewSchedule.aspx?v=c0976766-98a3-45cc-82df-e05b13129271"
                },
                {
                    "teacher_id": "2546",
                    "teacher_name": "Писаренко Андрій Володимирович",
                    "teacher_full_name": "старший викладач Писаренко Андрій Володимирович",
                    "teacher_short_name": "ст.вик. Писаренко А. В.",
                    "teacher_url": "http://rozklad.kpi.ua/Schedules/ViewSchedule.aspx?v=f9e88b1b-5935-4198-ae2f-b354302a13a7"
                }
            ],
            "rooms": [
                {
                    "room_id": "24",
                    "room_name": "534-18 Лаб",
                    "room_latitude": "50.447021",
                    "room_longitude": "30.456021"
                }
            ]
        },
        {
            "lesson_id": "6968",
            "group_id": "461",
            "day_number": "3",
            "day_name": "Середа",
            "lesson_name": "Цифр. СУ",
            "lesson_full_name": "Теорія автоматичного управління -2. Теорія цифрових систем управління",
            "lesson_number": "3",
            "lesson_room": "304-18",
            "lesson_type": "Лек",
            "teacher_name": "доц. Репнікова Н. Б.",
            "lesson_week": "1",
            "time_start": "12:20:00",
            "time_end": "13:55:00",
            "rate": "1",
            "teachers": [
                {
                    "teacher_id": "2768",
                    "teacher_name": "Репнікова Наталія Борисівна",
                    "teacher_full_name": "доцент Репнікова Наталія Борисівна",
                    "teacher_short_name": "доц. Репнікова Н. Б.",
                    "teacher_url": "http://rozklad.kpi.ua/Schedules/ViewSchedule.aspx?v=c0976766-98a3-45cc-82df-e05b13129271"
                }
            ],
            "rooms": [
                {
                    "room_id": "20",
                    "room_name": "304-18 Лек",
                    "room_latitude": "50.447021",
                    "room_longitude": "30.456021"
                }
            ]
        },
        {
            "lesson_id": "6973",
            "group_id": "461",
            "day_number": "3",
            "day_name": "Середа",
            "lesson_name": "Іст.укр.культ",
            "lesson_full_name": "Історія української культури",
            "lesson_number": "4",
            "lesson_room": "304-18",
            "lesson_type": "Лек",
            "teacher_name": "доц. Руденко Т. П.",
            "lesson_week": "1",
            "time_start": "14:15:00",
            "time_end": "15:50:00",
            "rate": "1",
            "teachers": [
                {
                    "teacher_id": "2841",
                    "teacher_name": "Руденко Тамара Петрівна",
                    "teacher_full_name": "доцент Руденко Тамара Петрівна",
                    "teacher_short_name": "доц. Руденко Т. П.",
                    "teacher_url": "http://rozklad.kpi.ua/Schedules/ViewSchedule.aspx?v=4fec1168-2096-404b-bd55-696516ac980b"
                }
            ],
            "rooms": [
                {
                    "room_id": "20",
                    "room_name": "304-18 Лек",
                    "room_latitude": "50.447021",
                    "room_longitude": "30.456021"
                }
            ]
        },
        {
            "lesson_id": "6960",
            "group_id": "461",
            "day_number": "4",
            "day_name": "Четвер",
            "lesson_name": "Екон-2",
            "lesson_full_name": "Економіка організації і планування виробництва-2. Економіка і організація виробництва",
            "lesson_number": "1",
            "lesson_room": "304-18",
            "lesson_type": "Лек",
            "teacher_name": "доц. Семенченко Н. В.",
            "lesson_week": "1",
            "time_start": "08:30:00",
            "time_end": "10:05:00",
            "rate": "1",
            "teachers": [
                {
                    "teacher_id": "2939",
                    "teacher_name": "Семенченко Н В",
                    "teacher_full_name": "доцент Семенченко Н В",
                    "teacher_short_name": "доц. Семенченко Н. В.",
                    "teacher_url": "http://rozklad.kpi.ua/Schedules/ViewSchedule.aspx?v=a0cf03e0-5213-4f89-b856-284367861187"
                }
            ],
            "rooms": [
                {
                    "room_id": "20",
                    "room_name": "304-18 Лек",
                    "room_latitude": "50.447021",
                    "room_longitude": "30.456021"
                }
            ]
        },
        {
            "lesson_id": "6964",
            "group_id": "461",
            "day_number": "4",
            "day_name": "Четвер",
            "lesson_name": "Комп.електр.2",
            "lesson_full_name": "Комп'ютерна електроніка-3. Мікропроцесорні системи",
            "lesson_number": "2",
            "lesson_room": "304-18",
            "lesson_type": "Лек",
            "teacher_name": "доц. Новацький А. О.",
            "lesson_week": "1",
            "time_start": "10:25:00",
            "time_end": "12:00:00",
            "rate": "1",
            "teachers": [
                {
                    "teacher_id": "2312",
                    "teacher_name": "Новацький Анатолій Олександрович",
                    "teacher_full_name": "доцент Новацький Анатолій Олександрович",
                    "teacher_short_name": "доц. Новацький А. О.",
                    "teacher_url": "http://rozklad.kpi.ua/Schedules/ViewSchedule.aspx?v=aaf53a6b-d63a-4997-8fc4-06c68223fa5c"
                }
            ],
            "rooms": [
                {
                    "room_id": "20",
                    "room_name": "304-18 Лек",
                    "room_latitude": "50.447021",
                    "room_longitude": "30.456021"
                }
            ]
        },
        {
            "lesson_id": "6969",
            "group_id": "461",
            "day_number": "4",
            "day_name": "Четвер",
            "lesson_name": "К.мет.досл.САУ",
            "lesson_full_name": "Комп'ютерні методи дослідження САУ",
            "lesson_number": "3",
            "lesson_room": "534-18",
            "lesson_type": "Лаб",
            "teacher_name": "ст.вик. Писаренко А. В., ас. Килимник О. М.",
            "lesson_week": "1",
            "time_start": "12:20:00",
            "time_end": "13:55:00",
            "rate": "1",
            "teachers": [
                {
                    "teacher_id": "2546",
                    "teacher_name": "Писаренко Андрій Володимирович",
                    "teacher_full_name": "старший викладач Писаренко Андрій Володимирович",
                    "teacher_short_name": "ст.вик. Писаренко А. В.",
                    "teacher_url": "http://rozklad.kpi.ua/Schedules/ViewSchedule.aspx?v=f9e88b1b-5935-4198-ae2f-b354302a13a7"
                },
                {
                    "teacher_id": "1351",
                    "teacher_name": "Килимник О. М.",
                    "teacher_full_name": "асистент Килимник О. М.",
                    "teacher_short_name": "ас. Килимник О. М.",
                    "teacher_url": "http://rozklad.kpi.ua/Schedules/ViewSchedule.aspx?v=d1ef0ddb-e84a-42e4-b18a-5872db12b928"
                }
            ],
            "rooms": [
                {
                    "room_id": "24",
                    "room_name": "534-18 Лаб",
                    "room_latitude": "50.447021",
                    "room_longitude": "30.456021"
                }
            ]
        },
        {
            "lesson_id": "6974",
            "group_id": "461",
            "day_number": "4",
            "day_name": "Четвер",
            "lesson_name": "ОПСПІ",
            "lesson_full_name": "Основи теорії інформаційних процесів-2.Основи побудови систем передачі інформації",
            "lesson_number": "4",
            "lesson_room": "517-18",
            "lesson_type": "Лаб",
            "teacher_name": "ст.вик. Моргаль О. М., ас. Дорошенко К. С.",
            "lesson_week": "1",
            "time_start": "14:15:00",
            "time_end": "15:50:00",
            "rate": "1",
            "teachers": [
                {
                    "teacher_id": "2185",
                    "teacher_name": "Моргаль Олег Михайлович",
                    "teacher_full_name": "старший викладач Моргаль Олег Михайлович",
                    "teacher_short_name": "ст.вик. Моргаль О. М.",
                    "teacher_url": "http://rozklad.kpi.ua/Schedules/ViewSchedule.aspx?v=48c84c9c-7af8-4c08-9c5a-4045aace8756"
                },
                {
                    "teacher_id": "972",
                    "teacher_name": "Дорошенко Катерина Сергіївна",
                    "teacher_full_name": "асистент Дорошенко Катерина Сергіївна",
                    "teacher_short_name": "ас. Дорошенко К. С.",
                    "teacher_url": "http://rozklad.kpi.ua/Schedules/ViewSchedule.aspx?v=b62429e2-150e-4bbc-81ee-02d78208f582"
                }
            ],
            "rooms": [
                {
                    "room_id": "22",
                    "room_name": "517-18 Лаб",
                    "room_latitude": "50.447021",
                    "room_longitude": "30.456021"
                }
            ]
        },
        {
            "lesson_id": "6965",
            "group_id": "461",
            "day_number": "5",
            "day_name": "П’ятниця",
            "lesson_name": "Екон-2",
            "lesson_full_name": "Економіка організації і планування виробництва-2. Економіка і організація виробництва",
            "lesson_number": "2",
            "lesson_room": "203-18",
            "lesson_type": "Прак",
            "teacher_name": "",
            "lesson_week": "1",
            "time_start": "10:25:00",
            "time_end": "12:00:00",
            "rate": "1",
            "teachers": [],
            "rooms": [
                {
                    "room_id": "25",
                    "room_name": "203-18 Прак",
                    "room_latitude": "50.447021",
                    "room_longitude": "30.456021"
                }
            ]
        },
        {
            "lesson_id": "6970",
            "group_id": "461",
            "day_number": "5",
            "day_name": "П’ятниця",
            "lesson_name": "Правознавство",
            "lesson_full_name": "Правознавство",
            "lesson_number": "3",
            "lesson_room": "304-18",
            "lesson_type": "Лек",
            "teacher_name": "",
            "lesson_week": "1",
            "time_start": "12:20:00",
            "time_end": "13:55:00",
            "rate": "1",
            "teachers": [],
            "rooms": [
                {
                    "room_id": "20",
                    "room_name": "304-18 Лек",
                    "room_latitude": "50.447021",
                    "room_longitude": "30.456021"
                }
            ]
        },
        {
            "lesson_id": "6975",
            "group_id": "461",
            "day_number": "5",
            "day_name": "П’ятниця",
            "lesson_name": "Ін. мова проф-1. Проф",
            "lesson_full_name": "Іноземна мова професійного спрямування -1. Іноземна мова професійного спрямування",
            "lesson_number": "4",
            "lesson_room": "531-18",
            "lesson_type": "Прак",
            "teacher_name": "ст.вик. Шевченко О. М.",
            "lesson_week": "1",
            "time_start": "14:15:00",
            "time_end": "15:50:00",
            "rate": "1",
            "teachers": [
                {
                    "teacher_id": "3719",
                    "teacher_name": "Шевченко Ольга Миколаївна",
                    "teacher_full_name": "старший викладач Шевченко Ольга Миколаївна",
                    "teacher_short_name": "ст.вик. Шевченко О. М.",
                    "teacher_url": "http://rozklad.kpi.ua/Schedules/ViewSchedule.aspx?v=e4882e95-01aa-4f5f-904c-1dc67efb8607"
                }
            ],
            "rooms": [
                {
                    "room_id": "21",
                    "room_name": "531-18 Прак",
                    "room_latitude": "50.447021",
                    "room_longitude": "30.456021"
                }
            ]
        },
        {
            "lesson_id": "6978",
            "group_id": "461",
            "day_number": "1",
            "day_name": "Понеділок",
            "lesson_name": "Ін. мова проф-1. Проф",
            "lesson_full_name": "Іноземна мова професійного спрямування -1. Іноземна мова професійного спрямування",
            "lesson_number": "2",
            "lesson_room": "531-18",
            "lesson_type": "Прак",
            "teacher_name": "",
            "lesson_week": "2",
            "time_start": "10:25:00",
            "time_end": "12:00:00",
            "rate": "1",
            "teachers": [],
            "rooms": [
                {
                    "room_id": "21",
                    "room_name": "531-18 Прак",
                    "room_latitude": "50.447021",
                    "room_longitude": "30.456021"
                }
            ]
        },
        {
            "lesson_id": "6983",
            "group_id": "461",
            "day_number": "1",
            "day_name": "Понеділок",
            "lesson_name": "ОПСПІ",
            "lesson_full_name": "Основи теорії інформаційних процесів-2.Основи побудови систем передачі інформації",
            "lesson_number": "3",
            "lesson_room": "307-18",
            "lesson_type": "Лек",
            "teacher_name": "ст.вик. Моргаль О. М.",
            "lesson_week": "2",
            "time_start": "12:20:00",
            "time_end": "13:55:00",
            "rate": "1",
            "teachers": [
                {
                    "teacher_id": "2185",
                    "teacher_name": "Моргаль Олег Михайлович",
                    "teacher_full_name": "старший викладач Моргаль Олег Михайлович",
                    "teacher_short_name": "ст.вик. Моргаль О. М.",
                    "teacher_url": "http://rozklad.kpi.ua/Schedules/ViewSchedule.aspx?v=48c84c9c-7af8-4c08-9c5a-4045aace8756"
                }
            ],
            "rooms": [
                {
                    "room_id": "23",
                    "room_name": "307-18 Лек",
                    "room_latitude": "50.447021",
                    "room_longitude": "30.456021"
                }
            ]
        },
        {
            "lesson_id": "6988",
            "group_id": "461",
            "day_number": "1",
            "day_name": "Понеділок",
            "lesson_name": "Іст.укр.культ",
            "lesson_full_name": "Історія української культури",
            "lesson_number": "4",
            "lesson_room": "231-18",
            "lesson_type": "Прак",
            "teacher_name": "вик. Дранник В. А.",
            "lesson_week": "2",
            "time_start": "14:15:00",
            "time_end": "15:50:00",
            "rate": "1",
            "teachers": [
                {
                    "teacher_id": "974",
                    "teacher_name": "Дранник Вікторія Анатоліївна",
                    "teacher_full_name": "викладач Дранник Вікторія Анатоліївна",
                    "teacher_short_name": "вик. Дранник В. А.",
                    "teacher_url": "http://rozklad.kpi.ua/Schedules/ViewSchedule.aspx?v=bf9c83e8-ab1a-4854-9f45-98cd28761468"
                }
            ],
            "rooms": [
                {
                    "room_id": "582",
                    "room_name": "231-18 Прак",
                    "room_latitude": "50.447021",
                    "room_longitude": "30.456021"
                }
            ]
        },
        {
            "lesson_id": "6979",
            "group_id": "461",
            "day_number": "2",
            "day_name": "Вівторок",
            "lesson_name": "Терія С та СА",
            "lesson_full_name": "Теорія систем та системний аналіз",
            "lesson_number": "2",
            "lesson_room": "304-18",
            "lesson_type": "Лек",
            "teacher_name": "доц. Кравець П. І.",
            "lesson_week": "2",
            "time_start": "10:25:00",
            "time_end": "12:00:00",
            "rate": "1",
            "teachers": [
                {
                    "teacher_id": "1629",
                    "teacher_name": "Кравець Петро Іванович",
                    "teacher_full_name": "доцент Кравець Петро Іванович",
                    "teacher_short_name": "доц. Кравець П. І.",
                    "teacher_url": "http://rozklad.kpi.ua/Schedules/ViewSchedule.aspx?v=2e64a2a9-39d1-4074-9af3-e9f09094fc3e"
                }
            ],
            "rooms": [
                {
                    "room_id": "20",
                    "room_name": "304-18 Лек",
                    "room_latitude": "50.447021",
                    "room_longitude": "30.456021"
                }
            ]
        },
        {
            "lesson_id": "6984",
            "group_id": "461",
            "day_number": "2",
            "day_name": "Вівторок",
            "lesson_name": "К.мет.досл.САУ",
            "lesson_full_name": "Комп'ютерні методи дослідження САУ",
            "lesson_number": "3",
            "lesson_room": "304-18",
            "lesson_type": "Лек",
            "teacher_name": "ст.вик. Писаренко А. В.",
            "lesson_week": "2",
            "time_start": "12:20:00",
            "time_end": "13:55:00",
            "rate": "1",
            "teachers": [
                {
                    "teacher_id": "2546",
                    "teacher_name": "Писаренко Андрій Володимирович",
                    "teacher_full_name": "старший викладач Писаренко Андрій Володимирович",
                    "teacher_short_name": "ст.вик. Писаренко А. В.",
                    "teacher_url": "http://rozklad.kpi.ua/Schedules/ViewSchedule.aspx?v=f9e88b1b-5935-4198-ae2f-b354302a13a7"
                }
            ],
            "rooms": [
                {
                    "room_id": "20",
                    "room_name": "304-18 Лек",
                    "room_latitude": "50.447021",
                    "room_longitude": "30.456021"
                }
            ]
        },
        {
            "lesson_id": "6980",
            "group_id": "461",
            "day_number": "3",
            "day_name": "Середа",
            "lesson_name": "Комп.електр.2",
            "lesson_full_name": "Комп'ютерна електроніка-3. Мікропроцесорні системи",
            "lesson_number": "2",
            "lesson_room": "517-18",
            "lesson_type": "Лаб",
            "teacher_name": "ст.вик. Катін П. Ю., ст.вик. Долина В. Г.",
            "lesson_week": "2",
            "time_start": "10:25:00",
            "time_end": "12:00:00",
            "rate": "1",
            "teachers": [
                {
                    "teacher_id": "1328",
                    "teacher_name": "Катін Павло Юрійович",
                    "teacher_full_name": "старший викладач Катін Павло Юрійович",
                    "teacher_short_name": "ст.вик. Катін П. Ю.",
                    "teacher_url": "http://rozklad.kpi.ua/Schedules/ViewSchedule.aspx?v=b083a31a-cc98-4d30-97ba-c4842c28e281"
                },
                {
                    "teacher_id": "957",
                    "teacher_name": "Долина Віктор Георгійович",
                    "teacher_full_name": "старший викладач Долина Віктор Георгійович",
                    "teacher_short_name": "ст.вик. Долина В. Г.",
                    "teacher_url": "http://rozklad.kpi.ua/Schedules/ViewSchedule.aspx?v=78a5b574-b05e-432b-919d-95f2f165ef36"
                }
            ],
            "rooms": [
                {
                    "room_id": "22",
                    "room_name": "517-18 Лаб",
                    "room_latitude": "50.447021",
                    "room_longitude": "30.456021"
                }
            ]
        },
        {
            "lesson_id": "6985",
            "group_id": "461",
            "day_number": "3",
            "day_name": "Середа",
            "lesson_name": "Цифр. СУ",
            "lesson_full_name": "Теорія автоматичного управління -2. Теорія цифрових систем управління",
            "lesson_number": "3",
            "lesson_room": "304-18",
            "lesson_type": "Лек",
            "teacher_name": "доц. Репнікова Н. Б.",
            "lesson_week": "2",
            "time_start": "12:20:00",
            "time_end": "13:55:00",
            "rate": "1",
            "teachers": [
                {
                    "teacher_id": "2768",
                    "teacher_name": "Репнікова Наталія Борисівна",
                    "teacher_full_name": "доцент Репнікова Наталія Борисівна",
                    "teacher_short_name": "доц. Репнікова Н. Б.",
                    "teacher_url": "http://rozklad.kpi.ua/Schedules/ViewSchedule.aspx?v=c0976766-98a3-45cc-82df-e05b13129271"
                }
            ],
            "rooms": [
                {
                    "room_id": "20",
                    "room_name": "304-18 Лек",
                    "room_latitude": "50.447021",
                    "room_longitude": "30.456021"
                }
            ]
        },
        {
            "lesson_id": "6976",
            "group_id": "461",
            "day_number": "4",
            "day_name": "Четвер",
            "lesson_name": "Екон-2",
            "lesson_full_name": "Економіка організації і планування виробництва-2. Економіка і організація виробництва",
            "lesson_number": "1",
            "lesson_room": "304-18",
            "lesson_type": "Лек",
            "teacher_name": "доц. Семенченко Н. В.",
            "lesson_week": "2",
            "time_start": "08:30:00",
            "time_end": "10:05:00",
            "rate": "1",
            "teachers": [
                {
                    "teacher_id": "2939",
                    "teacher_name": "Семенченко Н В",
                    "teacher_full_name": "доцент Семенченко Н В",
                    "teacher_short_name": "доц. Семенченко Н. В.",
                    "teacher_url": "http://rozklad.kpi.ua/Schedules/ViewSchedule.aspx?v=a0cf03e0-5213-4f89-b856-284367861187"
                }
            ],
            "rooms": [
                {
                    "room_id": "20",
                    "room_name": "304-18 Лек",
                    "room_latitude": "50.447021",
                    "room_longitude": "30.456021"
                }
            ]
        },
        {
            "lesson_id": "6981",
            "group_id": "461",
            "day_number": "4",
            "day_name": "Четвер",
            "lesson_name": "Комп.електр.2",
            "lesson_full_name": "Комп'ютерна електроніка-3. Мікропроцесорні системи",
            "lesson_number": "2",
            "lesson_room": "304-18",
            "lesson_type": "Лек",
            "teacher_name": "доц. Новацький А. О.",
            "lesson_week": "2",
            "time_start": "10:25:00",
            "time_end": "12:00:00",
            "rate": "1",
            "teachers": [
                {
                    "teacher_id": "2312",
                    "teacher_name": "Новацький Анатолій Олександрович",
                    "teacher_full_name": "доцент Новацький Анатолій Олександрович",
                    "teacher_short_name": "доц. Новацький А. О.",
                    "teacher_url": "http://rozklad.kpi.ua/Schedules/ViewSchedule.aspx?v=aaf53a6b-d63a-4997-8fc4-06c68223fa5c"
                }
            ],
            "rooms": [
                {
                    "room_id": "20",
                    "room_name": "304-18 Лек",
                    "room_latitude": "50.447021",
                    "room_longitude": "30.456021"
                }
            ]
        },
        {
            "lesson_id": "6986",
            "group_id": "461",
            "day_number": "4",
            "day_name": "Четвер",
            "lesson_name": "К.мет.досл.САУ",
            "lesson_full_name": "Комп'ютерні методи дослідження САУ",
            "lesson_number": "3",
            "lesson_room": "534-18",
            "lesson_type": "Лаб",
            "teacher_name": "ст.вик. Писаренко А. В., ас. Килимник О. М.",
            "lesson_week": "2",
            "time_start": "12:20:00",
            "time_end": "13:55:00",
            "rate": "1",
            "teachers": [
                {
                    "teacher_id": "2546",
                    "teacher_name": "Писаренко Андрій Володимирович",
                    "teacher_full_name": "старший викладач Писаренко Андрій Володимирович",
                    "teacher_short_name": "ст.вик. Писаренко А. В.",
                    "teacher_url": "http://rozklad.kpi.ua/Schedules/ViewSchedule.aspx?v=f9e88b1b-5935-4198-ae2f-b354302a13a7"
                },
                {
                    "teacher_id": "1351",
                    "teacher_name": "Килимник О. М.",
                    "teacher_full_name": "асистент Килимник О. М.",
                    "teacher_short_name": "ас. Килимник О. М.",
                    "teacher_url": "http://rozklad.kpi.ua/Schedules/ViewSchedule.aspx?v=d1ef0ddb-e84a-42e4-b18a-5872db12b928"
                }
            ],
            "rooms": [
                {
                    "room_id": "24",
                    "room_name": "534-18 Лаб",
                    "room_latitude": "50.447021",
                    "room_longitude": "30.456021"
                }
            ]
        },
        {
            "lesson_id": "6989",
            "group_id": "461",
            "day_number": "4",
            "day_name": "Четвер",
            "lesson_name": "ОПСПІ",
            "lesson_full_name": "Основи теорії інформаційних процесів-2.Основи побудови систем передачі інформації",
            "lesson_number": "4",
            "lesson_room": "517-18",
            "lesson_type": "Лаб",
            "teacher_name": "ст.вик. Моргаль О. М., ас. Дорошенко К. С.",
            "lesson_week": "2",
            "time_start": "14:15:00",
            "time_end": "15:50:00",
            "rate": "1",
            "teachers": [
                {
                    "teacher_id": "2185",
                    "teacher_name": "Моргаль Олег Михайлович",
                    "teacher_full_name": "старший викладач Моргаль Олег Михайлович",
                    "teacher_short_name": "ст.вик. Моргаль О. М.",
                    "teacher_url": "http://rozklad.kpi.ua/Schedules/ViewSchedule.aspx?v=48c84c9c-7af8-4c08-9c5a-4045aace8756"
                },
                {
                    "teacher_id": "972",
                    "teacher_name": "Дорошенко Катерина Сергіївна",
                    "teacher_full_name": "асистент Дорошенко Катерина Сергіївна",
                    "teacher_short_name": "ас. Дорошенко К. С.",
                    "teacher_url": "http://rozklad.kpi.ua/Schedules/ViewSchedule.aspx?v=b62429e2-150e-4bbc-81ee-02d78208f582"
                }
            ],
            "rooms": [
                {
                    "room_id": "22",
                    "room_name": "517-18 Лаб",
                    "room_latitude": "50.447021",
                    "room_longitude": "30.456021"
                }
            ]
        },
        {
            "lesson_id": "6977",
            "group_id": "461",
            "day_number": "5",
            "day_name": "П’ятниця",
            "lesson_name": "Терія С та СА",
            "lesson_full_name": "Теорія систем та системний аналіз",
            "lesson_number": "1",
            "lesson_room": "517-18",
            "lesson_type": "Лаб",
            "teacher_name": "ас. Шимкович В. М., ас. Тимофєєва Ю. С.",
            "lesson_week": "2",
            "time_start": "08:30:00",
            "time_end": "10:05:00",
            "rate": "1",
            "teachers": [
                {
                    "teacher_id": "3755",
                    "teacher_name": "Шимкович Володимир Миколайович",
                    "teacher_full_name": "асистент Шимкович Володимир Миколайович",
                    "teacher_short_name": "ас. Шимкович В. М.",
                    "teacher_url": "http://rozklad.kpi.ua/Schedules/ViewSchedule.aspx?v=05539928-025d-4f5a-98a0-e56bd6307f3e"
                },
                {
                    "teacher_id": "3267",
                    "teacher_name": "Тимофєєва Юлія Сергіївна",
                    "teacher_full_name": "асистент Тимофєєва Юлія Сергіївна",
                    "teacher_short_name": "ас. Тимофєєва Ю. С.",
                    "teacher_url": "http://rozklad.kpi.ua/Schedules/ViewSchedule.aspx?v=f2ce2479-3ec7-4786-a5c7-e7d43f3e4496"
                }
            ],
            "rooms": [
                {
                    "room_id": "22",
                    "room_name": "517-18 Лаб",
                    "room_latitude": "50.447021",
                    "room_longitude": "30.456021"
                }
            ]
        },
        {
            "lesson_id": "6982",
            "group_id": "461",
            "day_number": "5",
            "day_name": "П’ятниця",
            "lesson_name": "Екон-2",
            "lesson_full_name": "Економіка організації і планування виробництва-2. Економіка і організація виробництва",
            "lesson_number": "2",
            "lesson_room": "203-18",
            "lesson_type": "Прак",
            "teacher_name": "",
            "lesson_week": "2",
            "time_start": "10:25:00",
            "time_end": "12:00:00",
            "rate": "1",
            "teachers": [],
            "rooms": [
                {
                    "room_id": "25",
                    "room_name": "203-18 Прак",
                    "room_latitude": "50.447021",
                    "room_longitude": "30.456021"
                }
            ]
        },
        {
            "lesson_id": "6987",
            "group_id": "461",
            "day_number": "5",
            "day_name": "П’ятниця",
            "lesson_name": "Правознавство",
            "lesson_full_name": "Правознавство",
            "lesson_number": "3",
            "lesson_room": "304-18",
            "lesson_type": "Лек",
            "teacher_name": "",
            "lesson_week": "2",
            "time_start": "12:20:00",
            "time_end": "13:55:00",
            "rate": "1",
            "teachers": [],
            "rooms": [
                {
                    "room_id": "20",
                    "room_name": "304-18 Лек",
                    "room_latitude": "50.447021",
                    "room_longitude": "30.456021"
                }
            ]
        },
        {
            "lesson_id": "6990",
            "group_id": "461",
            "day_number": "5",
            "day_name": "П’ятниця",
            "lesson_name": "Ін. мова проф-1. Проф",
            "lesson_full_name": "Іноземна мова професійного спрямування -1. Іноземна мова професійного спрямування",
            "lesson_number": "4",
            "lesson_room": "531-18",
            "lesson_type": "Прак",
            "teacher_name": "ст.вик. Шевченко О. М.",
            "lesson_week": "2",
            "time_start": "14:15:00",
            "time_end": "15:50:00",
            "rate": "1",
            "teachers": [
                {
                    "teacher_id": "3719",
                    "teacher_name": "Шевченко Ольга Миколаївна",
                    "teacher_full_name": "старший викладач Шевченко Ольга Миколаївна",
                    "teacher_short_name": "ст.вик. Шевченко О. М.",
                    "teacher_url": "http://rozklad.kpi.ua/Schedules/ViewSchedule.aspx?v=e4882e95-01aa-4f5f-904c-1dc67efb8607"
                }
            ],
            "rooms": [
                {
                    "room_id": "21",
                    "room_name": "531-18 Прак",
                    "room_latitude": "50.447021",
                    "room_longitude": "30.456021"
                }
            ]
        }
    ]
}